Workbook

Sheet Start
B2: MEIFERTS · GUTACHTER-RECHENWERK
B3: Wertermittlung nach ImmoWertV 2021 · Prüfungswerkzeug ISO/IEC 17024 · Sachwert- und Ertragswertverfahren
B4: BEDIENUNG: Nur die GELBEN Felder ausfüllen. Alle übrigen Zellen sind gesperrt und rechnen automatisch. Fehleingaben werden blockiert.
B5: INHALT / BLÄTTER
B6: 01 Finanzmathematik | C6: Auf-/Abzinsung, Vervielfältiger, Renten- & Annuitätenfaktoren
B7: 02 Ertragswert – allgemein | C7: §§ 27–34 ImmoWertV · getrennte Boden-/Gebäudebetrachtung
B8: 03 Ertragswert – vereinfacht | C8: Reinertrag × V + abgezinster Bodenwert
B9: 04 Ertragswert – periodisch (DCF) | C9: Mehrperiodisch mit Restwert/Terminal Value
B10: 05 Sachwertverfahren | C10: §§ 35–39 · NHK 2010, Baupreisindex, Alterswertminderung, Sachwertfaktor
B11: 06 Vergleichs- & Bodenwert | C11: Bodenrichtwert, Umrechnungskoeffizient, Tiefenkorrektur
B12: 07 Liegenschaftszins | C12: Rückrechnung des LZ aus Kaufpreisen
B13: 08 Alterswertminderung | C13: Linear · Ross · modifiziertes Alter nach Modernisierung
B14: 09 Modernisierungspunkte | C14: ImmoWertV Anlage 2 · Punkteraster → modifizierte Restnutzungsdauer
B15: 10 Bewirtschaftungskosten | C15: Verwaltung, Instandhaltung, Mietausfallwagnis, n.u. Betriebskosten
B16: 11 Restwert & Liquidation | C16: Liquidations-, Restwertverzinsung, Zwischennutzung, Bauträger-Residual
B17: 12 Erbbaurecht | C17: Erbbauzins, Wert Erbbaurecht & Erbbaugrundstück (ErbbauRG)
... B24: 19 Faktortabellen | C24: Vervielfältiger- & Abzinsungstabellen 1–80 J. / 2–8 %
B26: BEDIENUNG
B27: › Gelbe Zellen = Eingaben (blaue Schrift). Diese Werte ändern Sie für Ihren Fall.
B28: › Schwarze/dunkle Zellen = Formeln. Nicht überschreiben – sie rechnen automatisch.
B29: › Dunkelblaue Ergebniszeilen = Endwerte des jeweiligen Verfahrens.
B30: › Alle Blätter sind unabhängig rechenbar; Vervielfältiger werden je Blatt selbst gebildet.
B31: › Rundung: Ergebnisse sind kaufmännisch zu runden; Marktwert i. d. R. auf volle 1.000 €.
B33: RECHTSGRUNDLAGEN
B34: • ImmoWertV 2021 (Immobilienwertermittlungsverordnung) – §§ 24–39
B35: • Vergleichswert §§ 24–26 · Ertragswert §§ 27–34 · Sachwert §§ 35–39
B36: • ErbbauRG · BelWertV · BauGB §§ 192 ff. (Gutachterausschüsse, Bodenrichtwerte)
B38: Werkzeug zur Prüfungsvorbereitung. Keine normativen NHK-/Vervielfältiger-Tabellen ersetzt; Tabellenwerte (NHK, Indizes, Sachwertfaktoren, Liegenschaftszins) sind objekt-/lageabhängig vom Gutachterausschuss zu übernehmen.

Sheet 01 Finanzmathematik
B2: FINANZMATHEMATIK · BARWERTFAKTOREN
B3: Grundlage aller Ertragswert- und Kapitalisierungsrechnungen · q = 1 + p
B5: EINGABE
B6: Zinssatz p (z. B. Liegenschaftszins) | C6: 0.05
B7: Laufzeit / Restnutzungsdauer n (Jahre) | C7: 50
B8: Zinsfaktor q = 1 + p | C8: =1+C6 -> 1.05
B10: FAKTOREN (nachschüssig)
B11: Aufzinsungsfaktor q^n | C11: =C8^C7 -> 11.4674 | D11: Endwert von 1 € heute nach n Jahren
B12: Abzinsungsfaktor q^-n | C12: =1/C8^C7 -> 0.087203727 | D12: Barwert von 1 € in n Jahren
B13: Rentenbarwertfaktor (Vervielfältiger) V | C13: =IF(C6=0,C7,(C8^C7-1)/(C8^C7*(C8-1))) -> 18.255925 | D13: Barwert einer Rente von 1 €/Jahr über n Jahre
B14: Rentenendwertfaktor | C14: =IF(C6=0,C7,(C8^C7-1)/(C8-1)) -> 209.348 | D14: Endwert einer Rente von 1 €/Jahr
B15: Kapitalwiedergewinnungs-/Annuitätenfaktor | C15: =IF(C6=0,1/C7,(C8^C7*(C8-1))/(C8^C7-1)) -> 0.054776735 | D15: = 1 / V · Annuität je 1 € Kapital
B16: Tilgungsfaktor (Restwertverzinsung) | C16: =IF(C6=0,1/C7,(C8-1)/(C8^C7-1)) -> 0.0047767355 | D16: Jährliche Tilgungsrate zur Ansammlung von 1 €
B18: ANWENDUNGSBEISPIEL
B19: Jährlicher Betrag (Rente / Reinertrag) | C19: 25000
B20: Barwert = Betrag × Vervielfältiger | C20: =C19*C13 -> 456398.14
B21: Einmalbetrag in n Jahren | C21: 100000
B22: Barwert heute = Betrag × Abzinsungsfaktor | C22: =C21*C12 -> 8720.3727
B24: V (Vervielfältiger) ist der zentrale Faktor im Ertragswertverfahren: Gebäudereinertrag × V = Gebäudeertragswert.
B25: FAKTOREN (VORSCHÜSSIG) · Zahlung zu Periodenbeginn
B26: Rentenbarwertfaktor vorschüssig (V × q) | C26: =C13*C8 -> 19.168722 | D26: Barwert einer vorschüssigen Rente von 1 €/Jahr
B27: Rentenendwertfaktor vorschüssig (REF × q) | C27: =C14*C8 -> 219.8154 | D27: Endwert einer vorschüssigen Rente
B28: Annuitätenfaktor vorschüssig (KWF / q) | C28: =C15/C8 -> 0.05216832 | D28: Annuität bei Zahlung im Voraus
B29: Vorschüssig = Zahlung zu Periodenbeginn (z. B. Erbbauzins, Mietvorauszahlung, vorschüssige Leibrente). Es gilt: vorschüssiger Faktor = nachschüssiger Faktor × q.
B31: INTERPOLIERTER VERVIELFÄLTIGER (lineare Tabelleninterpolation)
B32: Restnutzungsdauer n (Dezimal, z. B. 43,5) | C32: 43.5
B33: n unten (abgerundet) | C33: =ROUNDDOWN(C32,0) -> 43
B34: n oben (aufgerundet) | C34: =ROUNDUP(C32,0) -> 44
B35: Vervielfältiger bei n unten | C35: =IF($C$6=0,C33,(C8^C33-1)/(C8^C33*(C8-1))) -> 17.545912
B36: Vervielfältiger bei n oben | C36: =IF($C$6=0,C34,(C8^C34-1)/(C8^C34*(C8-1))) -> 17.662773
B37: interpolierter Vervielfältiger | C37: =IF(C34=C33,C35,C35+(C32-C33)*(C36-C35)) -> 17.604343
B38: Kontrolle: exakter Vervielfältiger (Formel) | C38: =IF($C$6=0,C32,(C8^C32-1)/(C8^C32*(C8-1))) -> 17.605055
B39: Die amtliche Vervielfältigertabelle ist nur für ganze Jahre angegeben. Für eine gebrochene Restnutzungsdauer wird zwischen den Tabellenwerten von n unten und n oben linear interpoliert. Die Kontrollzeile zeigt den exakten Formelwert. Zinssatz p und q werden oben (Eingabe) gesetzt.

Sheet 02 Ertragswert allgemein
B2: ERTRAGSWERTVERFAHREN · ALLGEMEIN
B3: §§ 27–34 ImmoWertV · getrennte Ermittlung von Bodenwert und Gebäudeertragswert
B5: EINGABEN
B6: Jahresrohertrag (marktüblich erzielbare Erträge) | C6: 60000
B7: Bewirtschaftungskosten gesamt | C7: 12000
B8: Bodenwert | C8: 300000
B9: Liegenschaftszinssatz p | C9: 0.045
B10: Restnutzungsdauer RND (Jahre) | C10: 45
B11: Zinsfaktor q = 1 + p | C11: =1+C9 -> 1.045
B12: Vervielfältiger V (q, RND) | C12: =IF(C9=0,C10,(C11^C10-1)/(C11^C10*(C11-1))) -> 19.156347
B13: BERECHNUNG
B14: Jahresrohertrag | C14: =C6 -> 60000
B15: abzgl. Bewirtschaftungskosten | C15: =-C7 -> -12000
B16: = Reinertrag des Grundstücks | C16: =C6-C7 -> 48000
B17: abzgl. Bodenwertverzinsung (Bodenwert × p) | C17: =-C8*C9 -> -13500
B18: = Gebäudereinertrag | C18: =C16-C8*C9 -> 34500
B19: Gebäudeertragswert (Geb.-Reinertrag × V) | C19: =C18*C12 -> 660893.99
B20: zzgl. Bodenwert | C20: =C8 -> 300000
B21: = vorläufiger Ertragswert | C21: =C19+C8 -> 960893.99
B22: ± besondere objektspez. Merkmale (boG) | C22: 0
B23: ERGEBNIS
B24: Ertragswert (= Marktwert i. S. § 6 Abs. 1) | C24: =C21+C22 -> 960893.99
B26: Reinertrag = Rohertrag − Bewirtschaftungskosten. Bodenwertverzinsung trennt den Bodenanteil ab; nur der Gebäudereinertrag wird über die Restnutzungsdauer kapitalisiert. Bodenwert wird voll addiert (zeitlich unbegrenzt nutzbar).

Sheet 03 Ertragswert vereinfacht
B2: ERTRAGSWERTVERFAHREN · VEREINFACHT
B3: Reinertrag × Vervielfältiger zzgl. auf die RND abgezinster Bodenwert
B5: EINGABEN
B6: Jahresrohertrag | C6: 60000
B7: Bewirtschaftungskosten gesamt | C7: 12000
B8: Bodenwert | C8: 300000
B9: Liegenschaftszinssatz p | C9: 0.045
B10: Restnutzungsdauer RND (Jahre) | C10: 45
B11: Zinsfaktor q = 1 + p | C11: =1+C9 -> 1.045
B12: Vervielfältiger V | C12: =IF(C9=0,C10,(C11^C10-1)/(C11^C10*(C11-1))) -> 19.156347
B13: Abzinsungsfaktor q^-n | C13: =1/C11^C10 -> 0.13796437
B14: BERECHNUNG
B15: Reinertrag des Grundstücks | C15: =C6-C7 -> 48000
B16: kapitalisierter Reinertrag (Reinertrag × V) | C16: =C15*C12 -> 919504.68
B17: abgezinster Bodenwert (Bodenwert × q^-n) | C17: =C8*C13 -> 41389.31
B18: ± besondere objektspez. Merkmale (boG) | C18: 0
B19: ERGEBNIS
B20: Ertragswert (vereinfacht) | C20: =C15*C12+C17+C18 -> 960893.99
B22: Im vereinfachten Verfahren wird der gesamte Reinertrag (inkl. Bodenanteil) kapitalisiert und der Bodenwert, der erst nach Ablauf der RND wieder „frei“ wird, auf den Stichtag abgezinst hinzugerechnet. Beide Ertragswertverfahren führen bei sauberer Eingabe zum selben Ergebnis.

Sheet 04 Ertragswert periodisch
B2: PERIODISCHES ERTRAGSWERTVERFAHREN (DCF)
B3: Mehrperiodische Diskontierung expliziter Cashflows zzgl. Restwert (Terminal Value)
B5: PARAMETER
B6: Diskontierungszinssatz p | C6: 0.05
B7: Detailbetrachtungszeitraum (Jahre, max. 10) | C7: 10
B8: Restwert am Ende (Terminal Value, undiskontiert) | C8: 650000 | E8: q = 1 + p | F8: =1+C6 -> 1.05
B10: CASHFLOW-REIHE
B11: Jahr t | C11: Reinertrag (€) | D11: Abzinsungsfaktor | E11: Barwert (€)
B12: 1 | C12: 48000 | D12: =IF(B12<=$C$7,1/$F$8^B12,0) -> 0.95238095 | E12: =C12*D12 -> 45714.286
B13: 2 | C13: 48960 | D13: =IF(B13<=$C$7,1/$F$8^B13,0) -> 0.90702948 | E13: =C13*D13 -> 44408.163
B14: 3 | C14: 49939 | D14: =IF(B14<=$C$7,1/$F$8^B14,0) -> 0.8638376 | E14: =C14*D14 -> 43139.186
B15: 4 | C15: 50938 | D15: =IF(B15<=$C$7,1/$F$8^B15,0) -> 0.82270247 | E15: =C15*D15 -> 41906.819
B16: 5 | C16: 51957 | D16: =IF(B16<=$C$7,1/$F$8^B16,0) -> 0.78352617 | E16: =C16*D16 -> 40709.669
B17: 6 | C17: 52996 | D17: =IF(B17<=$C$7,1/$F$8^B17,0) -> 0.7462154 | E17: =C17*D17 -> 39546.431
B18: 7 | C18: 54056 | D18: =IF(B18<=$C$7,1/$F$8^B18,0) -> 0.71068133 | E18: =C18*D18 -> 38416.59
B19: 8 | C19: 55137 | D19: =IF(B19<=$C$7,1/$F$8^B19,0) -> 0.67683936 | E19: =C19*D19 -> 37318.892
B20: 9 | C20: 56240 | D20: =IF(B20<=$C$7,1/$F$8^B20,0) -> 0.64460892 | E20: =C20*D20 -> 36252.805
B21: 10 | C21: 57364 | D21: =IF(B21<=$C$7,1/$F$8^B21,0) -> 0.61391325 | E21: =C21*D21 -> 35216.52
B22: RESTWERT & ERGEBNIS
B23: Summe Barwerte der Reinerträge | C23: =SUM(E12:E21) -> 402629.36
B24: Barwert des Restwerts (TV × q^-n) | C24: =C8/F8^C7 -> 399043.61
B25: ERGEBNIS
B26: Ertragswert (DCF) | C26: =C23+C24 -> 801672.98
B28: Jeder Reinertrag wird mit q^-t auf den Stichtag abgezinst; der Restwert am Ende des Detailzeitraums (z. B. vereinfachter Ertragswert oder Liquidationswert) wird ebenfalls abgezinst. Reinerträge jenseits des eingestellten Detailzeitraums werden automatisch ausgeblendet.

Sheet 05 Sachwertverfahren
B2: SACHWERTVERFAHREN
B3: §§ 35–39 ImmoWertV · NHK 2010, Baupreisindex, Alterswertminderung, Sachwertfaktor
B5: GEBÄUDEHERSTELLUNGSWERT
B6: Brutto-Grundfläche BGF (m²) | C6: 420
B7: Normalherstellungskosten NHK (€/m² BGF) | C7: 1450
B8: Baupreisindex (Stichtag, Basis 2010=100) | C8: 165
B9: Regionalfaktor | C9: 1
B10: Herstellungskosten (Normalherstellungswert) | C10: =C6*C7*(C8/100)*C9 -> 1004850
B11: ALTERSWERTMINDERUNG (linear)
B12: Gesamtnutzungsdauer GND (Jahre) | C12: 80
B13: Restnutzungsdauer RND (verwendet) | C13: =IF($F$14="Automatisch",ROUND('09 Modernisierungspunkte'!$C$30,0),$F$13) -> 50 | E13: ↳ RND manuell | F13: 55
B14: Restwertanteil RND / GND | C14: =C13/C12 -> 0.625 | E14: ↳ RND-Quelle | F14: Automatisch
B15: Alterswertminderung (1 − RND/GND) | C15: =-(1-C14)*C10 -> -376818.75
B16: = gealterter Gebäudewert | C16: =C10*C14 -> 628031.25
B17: WEITERE BESTANDTEILE
B18: zzgl. Außenanlagen | C18: 15000
B19: zzgl. besondere Bauteile / bauliche Anlagen | C19: 0
B20: zzgl. Bodenwert | C20: 300000
B21: = vorläufiger Sachwert | C21: =C16+C18+C19+C20 -> 943031.25
B22: MARKTANPASSUNG & ERGEBNIS
B23: Sachwertfaktor (Marktanpassungsfaktor) | C23: 1.1
B24: Sachwert (vorl. Sachwert × Sachwertfaktor) | C24: =C21*C23 -> 1037334.4
B25: ± besondere objektspez. Merkmale (boG) | C25: 0
B26: ERGEBNIS
B27: Sachwert (= Marktwert) | C27: =C24+C25 -> 1037334.4
B29: Reihenfolge § 39: Herstellungskosten → Alterswertminderung → + Außenanlagen + Bodenwert = vorläufiger Sachwert → × Sachwertfaktor (Marktanpassung) → ± boG = Sachwert/Marktwert. NHK stets über Baupreisindex auf den Stichtag anzupassen.

Sheet 06 Vergleichs- & Bodenwert
B2: VERGLEICHSWERT · BODENWERTERMITTLUNG
B3: §§ 24–26 ImmoWertV · Bodenrichtwert, Umrechnungskoeffizient, Tiefenkorrektur
B5: BODENWERT AUS BODENRICHTWERT
B6: Grundstücksfläche (m²) | C6: 500
B7: Bodenrichtwert (€/m²) | C7: 650
B8: GFZ des Bewertungsobjekts | C8: 0.8
B9: GFZ des Bodenrichtwertgrundstücks | C9: 1
B10: Umrechnungskoeffizient (GFZ-Anpassung) | C10: 0.9
B11: Tiefen-/Lagekorrektur | C11: 1
B12: Bereinigter Bodenwert (€/m²) | C12: =C7*C10*C11 -> 585
B13: Bodenwert gesamt | C13: =C6*C12 -> 292500
B14: ERGEBNIS
B15: Bodenwert | C15: =C13 -> 292500
B17: VERGLEICHSWERT AUS KAUFPREISEN
B18: Vergleichsobjekt | C18: Kaufpreis (€) | D18: Fläche (m²) | E18: Preis €/m²
B19: Vergleich 1 | C19: 340000 | D19: 520 | E19: =C19/D19 -> 653.84615
B20: Vergleich 2 | C20: 355000 | D20: 540 | E20: =C20/D20 -> 657.40741
B21: Vergleich 3 | C21: 330000 | D21: 505 | E21: =C21/D21 -> 653.46535
B22: Mittlerer Vergleichspreis (€/m²) | E22: =AVERAGE(E19:E21) -> 654.9063
B23: eigene Fläche (m²) | C23: 500
B24: Vergleichswert | C24: =E22*C23 -> 327453.15

Sheet 07 Liegenschaftszins
B2: LIEGENSCHAFTSZINSSATZ – ABLEITUNG
B3: Rückrechnung des LZ aus einem realisierten Kaufpreis (iterativ über Zielwertsuche)
B5: EINGABEN AUS DER VERGLEICHSTRANSAKTION
B6: Kaufpreis (= Ertragswert) | C6: 720000
B7: Jahresreinertrag | C7: 42000
B8: Bodenwert | C8: 300000
B9: Restnutzungsdauer RND (Jahre) | C9: 45
B10: Liegenschaftszins p (Startwert – iterieren) | C10: 0.045
B11: q = 1 + p | C11: =1+C10 -> 1.045
B12: Vervielfältiger V | C12: =IF(C10=0,C9,(C11^C9-1)/(C11^C9*(C11-1))) -> 19.156347
B13: PROBERECHNUNG
B14: Gebäudereinertrag (Reinertrag − Bodenwert×p) | C14: =C7-C8*C10 -> 28500
B15: errechneter Ertragswert (Geb.RE×V + Bodenwert) | C15: =C14*C12+C8 -> 845955.9
B16: Abweichung zum Kaufpreis (Ziel = 0) | C16: =C15-C6 -> 125955.9
B17: ERGEBNIS
B18: Abgeleiteter Liegenschaftszins | C18: =C10 -> 0.045
B20: Vorgehen: Zielwertsuche öffnen → Zielzelle C16, Zielwert 0, veränderbare Zelle C10. Excel ermittelt den Liegenschaftszins, bei dem der modellierte Ertragswert exakt dem realisierten Kaufpreis entspricht.

Sheet 08 Alterswertminderung
B2: ALTERSWERTMINDERUNG & RESTNUTZUNGSDAUER
B3: Linear · Ross · modifiziertes Alter nach Modernisierung
B5: GRUNDDATEN
B6: Gesamtnutzungsdauer GND (Jahre) | C6: 80
B7: Baujahr | C7: 1995
B8: Wertermittlungsstichtag (Jahr) | C8: 2026
B9: tatsächliches Gebäudealter | C9: =C8-C7 -> 31
B10: Herstellungskosten (Basis) | C10: 600000
B11: A · LINEARE ALTERSWERTMINDERUNG (ohne Modernisierung)
B12: Restnutzungsdauer GND − Alter | C12: =MAX(C6-C9,0) -> 49
B13: Alterswertminderung Alter/GND | C13: =C9/C6 -> 0.3875
B14: Wertminderungsbetrag | C14: =-C10*C9/C6 -> -232500
B15: verbleibender Gebäudewert | C15: =C10*(1-C9/C6) -> 367500
B16: B · ROSS (kombiniert linear/quadratisch)
B17: Wertminderung nach Ross | C17: =0.5*((C9/C6)+(C9/C6)^2) -> 0.26882812
B18: verbleibender Gebäudewert (Ross) | C18: =C10*(1-0.5*((C9/C6)+(C9/C6)^2)) -> 438703.12
B19: C · MODIFIZIERTES ALTER NACH MODERNISIERUNG
B20: verlängerte RND (verwendet) | C20: =IF($F$21="Automatisch",ROUND('09 Modernisierungspunkte'!$C$30,0),$F$20) -> 50 | E20: ↳ RND manuell | F20: 55
B21: modifiziertes (fiktives) Alter GND − RND_neu | C21: =C6-C20 -> 30 | E21: ↳ RND-Quelle | F21: Automatisch
B22: mod. Alterswertminderung fikt.Alter/GND | C22: =C21/C6 -> 0.375
B23: verbleibender Gebäudewert (modifiziert) | C23: =C10*(1-C21/C6) -> 375000
B25: Bei Modernisierung wird die Restnutzungsdauer geschätzt und daraus ein fiktives (modifiziertes) Gebäudealter (GND − RND_neu) abgeleitet. Dieses ersetzt das tatsächliche Alter in der linearen Wertminderung.

Sheet 09 Modernisierungspunkte
B2: MODERNISIERUNGSPUNKTE & MODIFIZIERTE RND
B3: ImmoWertV 2021 Anlage 2 · Punkteraster → wirtschaftliche Restnutzungsdauer
B5: GRUNDDATEN
B6: Gesamtnutzungsdauer GND (Jahre) | C6: 80
B7: tatsächliches Gebäudealter (Jahre) | C7: 40
B9: PUNKTERASTER NACH ImmoWertV ANLAGE 2
B10: Modernisierungselement | C10: max. Punkte | D10: erreicht
B11: Dacherneuerung inkl. Verbesserung der Wärmedämmung | C11: 4 | D11: 4
B12: Modernisierung der Fenster und Außentüren | C12: 2 | D12: 2
B13: Modernisierung der Leitungssysteme (Strom/Gas/Wasser/Abwasser) | C13: 2 | D13: 1
B14: Modernisierung der Heizungsanlage | C14: 2 | D14: 2
B15: Wärmedämmung der Außenwände | C15: 4 | D15: 2
B16: Modernisierung der Bäder | C16: 2 | D16: 1
B17: Modernisierung des Innenausbaus (Decken, Fußböden, Treppen) | C17: 2 | D17: 1
B18: Wesentliche Verbesserung der Grundrissgestaltung | C18: 2 | D18: 0
B19: Summe Punkte | C19: =SUM(C11:C18) -> 20 | D19: =SUM(D11:D18) -> 13
B21: MODERNISIERUNGSGRAD
B22: erreichte Punkte (max. 20) | C22: =D19 -> 13
B23: Einstufung | C23: =IF(D19<=1,"nicht modernisiert (0-1 P)",IF(D19<=5,"kleine Modernisierungen (2-5 P)",IF(D19<=10,"mittlerer Modernisierungsgrad (6-10 P)",IF(D19<=14,"überwiegend modernisiert (11-14 P)","umfassend modernisiert / kernsaniert (15-20 P)")))) -> überwiegend modernisiert (11-14 P)
B25: MODIFIZIERTE RESTNUTZUNGSDAUER (Interpolation nach Punkten)
B26: lineare Rest-ND ohne Modernisierung (GND − Alter) | C26: =MAX(C6-C7,0) -> 40
B27: Mindest-RND (Floor, falls genutzt/instandgehalten) | C27: 0
B28: max. erreichbare RND bei umfassender Mod. (Anker) | C28: =ROUND(0.7*C6,0) -> 56
B29: Gewicht (Punkte / 20) | C29: =D19/20 -> 0.65
B30: modifizierte Restnutzungsdauer | C30: =MAX(C27,C26,C26+(D19/20)*(C28-C26)) -> 50.4
B32: Punkteraster exakt nach ImmoWertV 2021 Anlage 2 (max. 20 Punkte). Die modifizierte RND wird transparent zwischen linearer Rest-ND (0 P) und der maximal erreichbaren RND bei umfassender Modernisierung (20 P) interpoliert. Alternativ den amtlichen RND-Wert der Anlage-2-Tabelle direkt als oberen Anker eintragen. Ergebnis in Blatt 05 (Sachwert) und Blatt 08 als RND übernehmen.

Sheet 10 Bewirtschaftungskosten
B2: BEWIRTSCHAFTUNGSKOSTEN
B3: Verwaltungs-, Instandhaltungs-, Mietausfallwagnis- und nicht umlegbare Betriebskosten
B5: BASIS
B6: Jahresrohertrag (Nettokaltmiete p. a.) | C6: 60000
B7: Wohn-/Nutzfläche (m²) | C7: 500
B8: KOSTENPOSITIONEN
B9: Position | C9: % vom Rohertrag | D9: Betrag (€)
B10: Verwaltungskosten | C10: 0.03 | D10: =$C$6*C10 -> 1800
B11: Instandhaltungskosten | C11: 0.08 | D11: =$C$6*C11 -> 4800
B12: Mietausfallwagnis | C12: 0.02 | D12: =$C$6*C12 -> 1200
B13: nicht umlegbare Betriebskosten | C13: 0.01 | D13: =$C$6*C13 -> 600
B14: Summe Bewirtschaftungskosten | C14: =SUM(C10:C13) -> 0.14 | D14: =SUM(D10:D13) -> 8400
B15: ERGEBNIS
B16: Reinertrag = Rohertrag − Bewirtschaftungskosten | C16: =C6-D14 -> 51600
B18: Den Summenbetrag (Zelle D14) in die Ertragswertblätter als „Bewirtschaftungskosten gesamt“ übernehmen. Instandhaltung kann alternativ als €/m² angesetzt werden – dann Prozentwert auf 0 setzen und Betrag direkt eintragen.

Sheet 11 Restwert & Liquidation
B2: RESTWERT-, LIQUIDATIONSWERT & RESTWERTVERZINSUNG
B3: Bodenwert nach Freilegung, Zwischennutzung und Abzinsung künftiger Werte
B5: A · LIQUIDATIONSWERT (Bodenwert nach Abriss)
B6: Bodenwert (baureif, nach Freilegung) | C6: 300000
B7: Freilegungs-/Abbruchkosten | C7: 45000
B8: Liquidationswert (sofort) | C8: =C6-C7 -> 255000
B9: B · RESTWERTVERZINSUNG / ABZINSUNG KÜNFTIGER WERTE
B10: Zeitraum bis Verwertung (Jahre) | C10: 8
B11: Zinssatz p | C11: 0.05
B12: q = 1 + p | C12: =1+C11 -> 1.05
B13: Abzinsungsfaktor q^-n | C13: =1/C12^C10 -> 0.67683936
B14: abgezinster Bodenwert | C14: =C6*C13 -> 203051.81
B15: abgezinste Freilegungskosten | C15: =-C7*C13 -> -30457.771
B16: Barwert Bodenanteil nach Verwertung | C16: =(C6-C7)*C13 -> 172594.04
B17: C · ZWISCHENNUTZUNG BIS VERWERTUNG
B18: Jahresreinertrag während Zwischennutzung | C18: 18000
B19: Vervielfältiger V (p, Zwischennutzungsdauer) | C19: =IF(C11=0,C10,(C12^C10-1)/(C12^C10*(C12-1))) -> 6.4632128
B20: Barwert Zwischennutzung (Reinertrag × V) | C20: =C18*C19 -> 116337.83
B21: ERGEBNIS
B22: Objektwert = Zwischennutzung + abgez. Bodenanteil | C22: =C20+C16 -> 288931.87
B24: Anwendung bei abgängiger Bausubstanz / wirtschaftlicher Überalterung: laufender Reinertrag der Zwischennutzung wird kapitalisiert, der erst nach Abriss/Verwertung realisierbare Bodenwert (abzgl. Freilegung) auf den Stichtag abgezinst. Bei sofort wirtschaftlicher Verwertung ist der Liquidationswert (A) maßgeblich.
B26: D · BAUTRÄGER-RESIDUALWERT (Grundstückspreis aus Projektentwicklung)
B27: erzielbarer Verkaufserlös (netto) | C27: 1200000
B28: abzgl. Baukosten inkl. Baunebenkosten | C28: 720000
B29: abzgl. Vermarktungs-/Vertriebskosten (% vom Erlös) | C29: 0.05
B30: abzgl. Finanzierungskosten | C30: 40000
B31: abzgl. Wagnis & Gewinn (% vom Erlös) | C31: 0.15
B32: = tragfähige Grundstücksinvestition (brutto, inkl. ENK) | C32: =C27-C28-C27*C29-C30-C27*C31 -> 200000
B33: Erwerbsnebenkosten Grundstück (%) | C33: 0.07
B34: Grundstückswert (Residual, netto) | C34: =C32/(1+C33) -> 186915.89
B36: Residualwertverfahren der Projektentwicklung: Vom erzielbaren Verkaufserlös werden Baukosten, Vertriebs- und Finanzierungskosten sowie Wagnis & Gewinn abgezogen; der Rest ist die tragfähige Grundstücksinvestition. Herausrechnen der Erwerbsnebenkosten ergibt den maximal vertretbaren Grundstückskaufpreis.

Sheet 12 Erbbaurecht
B2: ERBBAURECHT (ErbbauRG)
B3: Finanzmathematische Bewertung von Erbbaurecht und Erbbaugrundstück
B5: EINGABEN
B6: Bodenwert (volles Eigentum) | C6: 300000
B7: Gebäude-/Bauwerkswert (Ertrags-/Sachwert) | C7: 400000
B8: vereinbarter Erbbauzins p. a. | C8: 9000
B9: angemessener Bodenwertzins (Liegenschaftszins) | C9: 0.04
B10: Restlaufzeit Erbbaurecht (Jahre) | C10: 60
B11: Entschädigung bei Heimfall (% des Gebäudewerts) | C11: 1
B12: q = 1 + p | C12: =1+C9 -> 1.04
B13: Vervielfältiger V | C13: =IF(C9=0,C10,(C12^C10-1)/(C12^C10*(C12-1))) -> 22.62349
B14: Abzinsungsfaktor q^-n | C14: =1/C12^C10 -> 0.095060401
B15: ANGEMESSENER vs. VEREINBARTER ERBBAUZINS
B16: angemessener Erbbauzins (Bodenwert × Zins) | C16: =C6*C9 -> 12000
B17: Erbbauzinsvorteil/-nachteil p. a. (angem. − vereinb.) | C17: =C16-C8 -> 3000
B18: WERT DES ERBBAURECHTS (Erbbauberechtigter)
B19: Gebäudewert | C19: =C7 -> 400000
B20: + Barwert Erbbauzinsvorteil (Vorteil × V) | C20: =C17*C13 -> 67870.47
B21: − abgezinster Heimfallverlust am Ende | C21: =-C7*(1-C11)*C14 -> 0
B22: Wert des Erbbaurechts | C22: =C7+C17*C13-C7*(1-C11)*C14 -> 467870.47
B23: WERT DES ERBBAUGRUNDSTÜCKS (Eigentümer/Verpflichteter)
B24: Barwert der Erbbauzinszahlungen (Zins × V) | C24: =C8*C13 -> 203611.41
B25: + abgezinster Bodenwert (Heimfall) | C25: =C6*C14 -> 28518.12
B26: + abgez. Entschädigungsanteil ./. (entfällt Eigentümer) | C26: 0
B27: Wert des Erbbaugrundstücks | C27: =C8*C13+C6*C14 -> 232129.53
B29: Vereinfachtes finanzmathematisches Modell: Der Erbbauberechtigte hält den Gebäudewert plus/minus den Barwert der Erbbauzins-Differenz, abzgl. des bei Heimfall nicht entschädigten Gebäudeanteils. Der Grundstückseigentümer hält den Barwert der Erbbauzinsen plus den auf den Heimfallzeitpunkt abgezinsten Bodenwert. Vertragsklauseln (Anpassung, Heimfall) im Einzelfall prüfen.

Sheet 13 Rechte & Belastungen
B2: RECHTE & BELASTUNGEN – KAPITALISIERUNG
B3: Wohnungsrecht, Nießbrauch, Leibrente, wiederkehrende Lasten
B5: PARAMETER
B6: Kapitalisierungszinssatz p | C6: 0.045
B7: q = 1 + p | C7: =1+C6 -> 1.045
B8: A · BEFRISTETES RECHT (feste Laufzeit)
B9: Jahreswert des Rechts (z. B. Mietwert Wohnrecht) | C9: 9600
B10: Laufzeit (Jahre) | C10: 15
B11: Vervielfältiger V (p, Laufzeit) | C11: =IF(C6=0,C10,(C7^C10-1)/(C7^C10*(C7-1))) -> 10.739546
B12: Kapitalwert des Rechts | C12: =C9*C11 -> 103099.64
B13: B · LEBENSLÄNGLICHES RECHT (Leibrente / Nießbrauch)
B14: Jahreswert (Nutzungs-/Rentenwert) | C14: 9600
B15: Leibrentenbarwertfaktor (Kapitalwert lt. Tabelle) | C15: 12.5
B16: Kapitalwert des lebenslänglichen Rechts | C16: =C14*C15 -> 120000
B17: C · WERTMINDERUNG DES GRUNDSTÜCKS
B18: unbelasteter Verkehrswert | C18: 500000
B19: Kapitalwert der Belastung (aus A oder B übernehmen) | C19: 120000
B20: belasteter Verkehrswert | C20: =C18-C19 -> 380000
B22: Befristete Rechte werden mit dem Vervielfältiger der Laufzeit kapitalisiert; lebenslängliche Rechte mit dem altersabhängigen Leibrentenbarwertfaktor (amtliche Tabelle). Der Kapitalwert mindert den unbelasteten Verkehrswert.

Sheet 14 Beleihungswert
B2: BELEIHUNGSWERT (BelWertV)
B3: Nachhaltig erzielbarer Wert · Ertrags- und Sachwert mit Sicherheitsabschlägen
B5: ERTRAGSWERT (BelWertV)
B6: nachhaltiger Jahresrohertrag | C6: 58000
B7: Bewirtschaftungskosten (mind. Ansätze BelWertV) | C7: 13000
B8: Reinertrag | C8: =C6-C7 -> 45000
B9: Bodenwert (vorsichtig) | C9: 290000
B10: Kapitalisierungszins (BelWertV-Mindestsatz) | C10: 0.06
B11: Restnutzungsdauer (Jahre) | C11: 40
B12: q = 1 + p | C12: =1+C10 -> 1.06
B13: Vervielfältiger V | C13: =IF(C10=0,C11,(C12^C11-1)/(C12^C11*(C12-1))) -> 15.046297
B14: Gebäudereinertrag (Reinertrag − Bodenwert×p) | C14: =C8-C9*C10 -> 27600
B15: Ertragsbeleihungswert (vorl.) | C15: =C14*C13+C9 -> 705277.79
B16: SACHWERT (BelWertV) – Kontrolle
B17: vorläufiger Sachwert | C17: 720000
B18: Sicherheitsabschlag | C18: 0.1
B19: Sachbeleihungswert | C19: =C17*(1-C18) -> 648000
B20: ERGEBNIS
B21: Beleihungswert (i. d. R. der niedrigere Wert) | C21: =MIN(C15,C19) -> 648000
B23: Der Beleihungswert nach BelWertV ist konservativ: nachhaltige Mieten, Mindest-Bewirtschaftungskosten, Mindest-Kapitalisierungszinssätze und Sicherheitsabschläge. Maßgeblich ist regelmäßig der niedrigere aus Ertrags- und Sachbeleihungswert.

Sheet 15 Interpolation
B2: INTERPOLATION
B3: Lineare und bilineare Interpolation für Tabellenwerte (Vervielfältiger, Sachwertfaktor, Liegenschaftszins)
B5: A · LINEARE INTERPOLATION y = y1 + (x−x1)/(x2−x1) · (y2−y1)
B6: Stützstelle x1 (z. B. RND 40) | C6: 40
B7: Wert y1 (z. B. Vervielfältiger bei 40) | C7: 17.159
B8: Stützstelle x2 (z. B. RND 45) | C8: 45
B9: Wert y2 (z. B. Vervielfältiger bei 45) | C9: 18.402
B10: Zielstelle x (z. B. RND 43) | C10: 43
B11: interpolierter Wert y | C11: =IF(C8=C6,C7,C7+(C10-C6)/(C8-C6)*(C9-C7)) -> 17.9048
B13: Anwendung für Zwischenwerte in Vervielfältiger-, Abzinsungs-, Sachwertfaktor-, Umrechnungskoeffizienten- oder Liegenschaftszins-Tabellen. x = unabhängige Größe (RND oder Zinssatz), y = abzulesender Faktor.
B15: B · BILINEARE INTERPOLATION (2D-Tabellen, z. B. Sachwertfaktor)
B16: x1 (linke Spaltenstützstelle) | C16: 300
B17: x2 (rechte Spaltenstützstelle) | C17: 500
B18: y1 (obere Zeilenstützstelle) | C18: 400000
B19: y2 (untere Zeilenstützstelle) | C19: 600000
B20: f(x1,y1) Ecke oben-links | C20: 1.12
B21: f(x2,y1) Ecke oben-rechts | C21: 1.08
B22: f(x1,y2) Ecke unten-links | C22: 1.08
B23: f(x2,y2) Ecke unten-rechts | C23: 1.05
B24: Zielstelle x | C24: 420
B25: Zielstelle y | C25: 500000
B26: t = (x−x1)/(x2−x1) | C26: =IF(C17=C16,0,(C24-C16)/(C17-C16)) -> 0.6
B27: u = (y−y1)/(y2−y1) | C27: =IF(C19=C18,0,(C25-C18)/(C19-C18)) -> 0.5
B28: bilinear interpolierter Wert | C28: =C20*(1-C26)*(1-C27)+C21*C26*(1-C27)+C22*(1-C26)*C27+C23*C26*C27 -> 1.079
B30: Für 2D-Tabellen (Sachwertfaktor über Bodenrichtwert × vorläufigem Sachwert): die vier umliegenden Tabellenwerte und ihre Stützstellen eintragen. Blatt 16 wendet dies automatisch auf eine Beispielmatrix an.

Sheet 16 Sachwertfaktor-Matrix
B2: SACHWERTFAKTOR-MATRIX (bilinear)
B3: Marktanpassungsfaktor in Abhängigkeit von Bodenrichtwert und vorläufigem Sachwert
B5: BEISPIELMATRIX · Spalten = Bodenrichtwert (€/m²) · Zeilen = vorläufiger Sachwert (€)
B6: Beispielwerte – durch die Sachwertfaktoren des zuständigen Gutachterausschusses ersetzen.
B8: vorl. Sachwert \ BRW | C8: 100 | D8: 300 | E8: 500 | F8: 700
B9: 200000 | C9: 1.2 | D9: 1.15 | E9: 1.1 | F9: 1.05
B10: 400000 | C10: 1.15 | D10: 1.12 | E10: 1.08 | F10: 1.04
B11: 600000 | C11: 1.1 | D11: 1.08 | E11: 1.05 | F11: 1.02
B12: 800000 | C12: 1.05 | D12: 1.04 | E12: 1.02 | F12: 1
B13: 1000000 | C13: 1.02 | D13: 1.01 | E13: 1 | F13: 0.98
B15: ABLESUNG (automatische bilineare Interpolation)
B16: vorläufiger Sachwert (Ziel) € | C16: 520000
B17: Bodenrichtwert (Ziel) €/m² | C17: 420
B19: › geklemmter BRW | C19: =MEDIAN($C$8,C17,$F$8) -> 420
B20: › Spalte links / rechts | C20: =MATCH(C19,$C$8:$F$8,1) -> 2 | D20: =MIN(C20+1,4) -> 3
B21: › geklemmter Sachwert | C21: =MEDIAN($B$9,C16,$B$13) -> 520000
B22: › Zeile oben / unten | C22: =MATCH(C21,$B$9:$B$13,1) -> 2 | D22: =MIN(C22+1,5) -> 3
B23: › t / u | C23: =IF(INDEX($C$8:$F$8,1,D20)=INDEX($C$8:$F$8,1,C20),0,(C19-INDEX($C$8:$F$8,1,C20))/(INDEX($C$8:$F$8,1,D20)-INDEX($C$8:$F$8,1,C20))) -> 0.6 | D23: =IF(INDEX($B$9:$B$13,D22,1)=INDEX($B$9:$B$13,C22,1),0,(C21-INDEX($B$9:$B$13,C22,1))/(INDEX($B$9:$B$13,D22,1)-INDEX($B$9:$B$13,C22,1))) -> 0.6
B25: abgelesener Sachwertfaktor | C25: =INDEX($C$9:$F$13,C22,C20)*(1-C23)*(1-D23)+INDEX($C$9:$F$13,C22,D20)*C23*(1-D23)+INDEX($C$9:$F$13,D22,C20)*(1-C23)*D23+INDEX($C$9:$F$13,D22,D20)*C23*D23 -> 1.0756
B26: → Sachwert = vorläufiger Sachwert × Faktor | C26: =C16*C25 -> 559312
B28: Die Ablesung interpoliert bilinear zwischen den vier umliegenden Matrixwerten. Werte außerhalb der Matrix werden auf den Randwert geklemmt. Matrix und Stützstellen frei editierbar.

Sheet 17 GND & NHK Referenz
B2: GND- & NHK-REFERENZ
B3: Orientierungswerte für Gesamtnutzungsdauer und NHK-Standardstufen
B5: GESAMTNUTZUNGSDAUER (GND) — Orientierungswerte
B6: Gebäudetyp | C6: GND (Jahre)
B7: Ein-/Zweifamilienhäuser (freistehend) | C7: 70–80
B8: Reihen- und Doppelhäuser | C8: 70–80
B9: Mehrfamilienhäuser | C9: 70–80
B10: Wohnhäuser mit Mischnutzung | C10: 60–70
B11: Büro- und Geschäftshäuser | C11: 50–60
B12: Verbrauchermärkte / Discounter | C12: 30–40
B13: Hallen- und Lagergebäude | C13: 40–60
B14: Hotels | C14: 40–50
B15: Parkhäuser / Tiefgaragen | C15: 40–60
B16: Orientierungswerte; maßgeblich sind die GND-Ansätze der ImmoWertV-Anlagen bzw. das begründete Sachverständigenermessen.
B18: NHK-STANDARDSTUFEN (Prinzip)
B19: Standardstufe | C19: Ausstattungs-/Baustandard
B20: Stufe 1 | C20: sehr einfacher Standard
B21: Stufe 2 | C21: einfacher Standard
B22: Stufe 3 | C22: mittlerer / durchschnittlicher Standard
B23: Stufe 4 | C23: gehobener Standard
B24: Stufe 5 | C24: aufwendiger / stark gehobener Standard
B25: Konkrete NHK 2010 (€/m² BGF) je Gebäudeart und Standardstufe aus den NHK-Tabellen entnehmen; stets über den Baupreisindex auf den Stichtag umrechnen.
B27: NHK-SCHNELLUMRECHNUNG
B28: NHK 2010 (€/m² BGF, Basisjahr 2010 = 100) | C28: 1450
B29: Baupreisindex zum Stichtag | C29: 165
B30: Regionalfaktor | C30: 1
B31: NHK zum Stichtag (€/m² BGF) | C31: =C28*C29/100*C30 -> 2392.5

Sheet 18 Verkehrswert-Zusammenführung
B2: VERKEHRSWERT-ZUSAMMENFÜHRUNG
B3: Gewichtete Zusammenführung der Wertermittlungsverfahren (§§ 6, 8 ImmoWertV)
B5: ERGEBNISSE DER VERFAHREN (verknüpft)
B6: Vergleichswert (Blatt 06) | C6: ='06 Vergleichs- & Bodenwert'!C24 -> 327453.15
B7: Ertragswert (Blatt 02) | C7: ='02 Ertragswert allgemein'!C24 -> 960893.99
B8: Sachwert (Blatt 05) | C8: ='05 Sachwertverfahren'!C27 -> 1037334.4
B10: GEWICHTUNG
B11: Verfahren | C11: Wert (€) | D11: Gewicht | E11: Beitrag (€)
B12: Vergleichswert | C12: =C6 -> 327453.15 | D12: 0 | E12: =C12*D12 -> 0
B13: Ertragswert | C13: =C7 -> 960893.99 | D13: 0.6 | E13: =C13*D13 -> 576536.39
B14: Sachwert | C14: =C8 -> 1037334.4 | D14: 0.4 | E14: =C14*D14 -> 414933.75
B15: Summe | D15: =SUM(D12:D14) -> 1 | E15: =SUM(E12:E14) -> 991470.14
B16: Prüfung: Summe Gewichte = 100 % | D16: =IF(ABS(D15-1)<0.0001,"OK","≠ 100%") -> OK
B18: ERGEBNIS
B19: gewichteter Verkehrswert | C19: =E15 -> 991470.14
B20: gewählter Verkehrswert (gerundet) | C20: =ROUND(C19,-3) -> 991000
B22: Begründung der Gewichtung | C22: Marktüblich für diese Objektart: Ertragswert führend, Sachwert stützend. Vergleichswert nachrangig mangels Vergleichsfällen.
B27: Die Verfahren werden nicht schematisch gemittelt, sondern nach Aussagekraft im Einzelfall gewichtet (§ 6 Abs. 1 ImmoWertV). Die Gewichtung ist im Gutachten zu begründen. Werte werden live aus den Blättern 02, 05 und 06 gezogen.

Sheet 19 Faktortabellen
B2: FAKTORTABELLEN
B3: Vervielfältiger V (Rentenbarwertfaktor) und Abzinsungsfaktor q^-n nach n und p
B5: VERVIELFÄLTIGER V = (qⁿ−1) / (qⁿ·(q−1)) · Spalten = Zinssatz p
B6: n \ p | C6: 0.02 | D6: 0.025 | E6: 0.03 | F6: 0.035 | G6: 0.04 | H6: 0.045 | I6: 0.05 | J6: 0.06 | K6: 0.07 | L6: 0.08
B7: 5 | C7: =((1+0.02)^5-1)/((1+0.02)^5*0.02) -> 4.7134595 | D7: =((1+0.025)^5-1)/((1+0.025)^5*0.025) -> 4.6458285 | E7: =((1+0.03)^5-1)/((1+0.03)^5*0.03) -> 4.5797072 | F7: =((1+0.035)^5-1)/((1+0.035)^5*0.035) -> 4.5150524 | G7: =((1+0.04)^5-1)/((1+0.04)^5*0.04) -> 4.4518223 | H7: =((1+0.045)^5-1)/((1+0.045)^5*0.045) -> 4.3899767 | I7: =((1+0.05)^5-1)/((1+0.05)^5*0.05) -> 4.3294767 | J7: =((1+0.06)^5-1)/((1+0.06)^5*0.06) -> 4.2123638 | K7: =((1+0.07)^5-1)/((1+0.07)^5*0.07) -> 4.1001974 | L7: =((1+0.08)^5-1)/((1+0.08)^5*0.08) -> 3.99271
B8: 10 | C8: =((1+0.02)^10-1)/((1+0.02)^10*0.02) -> 8.982585 | D8: =((1+0.025)^10-1)/((1+0.025)^10*0.025) -> 8.7520639 | E8: =((1+0.03)^10-1)/((1+0.03)^10*0.03) -> 8.5302028 | F8: =((1+0.035)^10-1)/((1+0.035)^10*0.035) -> 8.3166053 | G8: =((1+0.04)^10-1)/((1+0.04)^10*0.04) -> 8.1108958 | H8: =((1+0.045)^10-1)/((1+0.045)^10*0.045) -> 7.9127182 | I8: =((1+0.05)^10-1)/((1+0.05)^10*0.05) -> 7.7217349 | J8: =((1+0.06)^10-1)/((1+0.06)^10*0.06) -> 7.3600871 | K8: =((1+0.07)^10-1)/((1+0.07)^10*0.07) -> 7.0235815 | L8: =((1+0.08)^10-1)/((1+0.08)^10*0.08) -> 6.7100814
B9: 15 | C9: =((1+0.02)^15-1)/((1+0.02)^15*0.02) -> 12.849264 | D9: =((1+0.025)^15-1)/((1+0.025)^15*0.025) -> 12.381378 | E9: =((1+0.03)^15-1)/((1+0.03)^15*0.03) -> 11.937935 | F9: =((1+0.035)^15-1)/((1+0.035)^15*0.035) -> 11.517411 | G9: =((1+0.04)^15-1)/((1+0.04)^15*0.04) -> 11.118387 | H9: =((1+0.045)^15-1)/((1+0.045)^15*0.045) -> 10.739546 | I9: =((1+0.05)^15-1)/((1+0.05)^15*0.05) -> 10.379658 | J9: =((1+0.06)^15-1)/((1+0.06)^15*0.06) -> 9.712249 | K9: =((1+0.07)^15-1)/((1+0.07)^15*0.07) -> 9.107914 | L9: =((1+0.08)^15-1)/((1+0.08)^15*0.08) -> 8.5594787
B10: 20 | C10: =((1+0.02)^20-1)/((1+0.02)^20*0.02) -> 16.351433 | D10: =((1+0.025)^20-1)/((1+0.025)^20*0.025) -> 15.589162 | E10: =((1+0.03)^20-1)/((1+0.03)^20*0.03) -> 14.877475 | F10: =((1+0.035)^20-1)/((1+0.035)^20*0.035) -> 14.212403 | G10: =((1+0.04)^20-1)/((1+0.04)^20*0.04) -> 13.590326 | H10: =((1+0.045)^20-1)/((1+0.045)^20*0.045) -> 13.007936 | I10: =((1+0.05)^20-1)/((1+0.05)^20*0.05) -> 12.46221 | J10: =((1+0.06)^20-1)/((1+0.06)^20*0.06) -> 11.469921 | K10: =((1+0.07)^20-1)/((1+0.07)^20*0.07) -> 10.594014 | L10: =((1+0.08)^20-1)/((1+0.08)^20*0.08) -> 9.8181474
B11: 25 | C11: =((1+0.02)^25-1)/((1+0.02)^25*0.02) -> 19.523456 | D11: =((1+0.025)^25-1)/((1+0.025)^25*0.025) -> 18.424376 | E11: =((1+0.03)^25-1)/((1+0.03)^25*0.03) -> 17.413148 | F11: =((1+0.035)^25-1)/((1+0.035)^25*0.035) -> 16.481515 | G11: =((1+0.04)^25-1)/((1+0.04)^25*0.04) -> 15.62208 | H11: =((1+0.045)^25-1)/((1+0.045)^25*0.045) -> 14.828209 | I11: =((1+0.05)^25-1)/((1+0.05)^25*0.05) -> 14.093945 | J11: =((1+0.06)^25-1)/((1+0.06)^25*0.06) -> 12.783356 | K11: =((1+0.07)^25-1)/((1+0.07)^25*0.07) -> 11.653583 | L11: =((1+0.08)^25-1)/((1+0.08)^25*0.08) -> 10.674776
B12: 30 | C12: =((1+0.02)^30-1)/((1+0.02)^30*0.02) -> 22.396456 | D12: =((1+0.025)^30-1)/((1+0.025)^30*0.025) -> 20.930293 | E12: =((1+0.03)^30-1)/((1+0.03)^30*0.03) -> 19.600441 | F12: =((1+0.035)^30-1)/((1+0.035)^30*0.035) -> 18.392045 | G12: =((1+0.04)^30-1)/((1+0.04)^30*0.04) -> 17.292033 | H12: =((1+0.045)^30-1)/((1+0.045)^30*0.045) -> 16.288889 | I12: =((1+0.05)^30-1)/((1+0.05)^30*0.05) -> 15.372451 | J12: =((1+0.06)^30-1)/((1+0.06)^30*0.06) -> 13.764831 | K12: =((1+0.07)^30-1)/((1+0.07)^30*0.07) -> 12.409041 | L12: =((1+0.08)^30-1)/((1+0.08)^30*0.08) -> 11.257783
B13: 35 | C13: =((1+0.02)^35-1)/((1+0.02)^35*0.02) -> 24.998619 | D13: =((1+0.025)^35-1)/((1+0.025)^35*0.025) -> 23.145157 | E13: =((1+0.03)^35-1)/((1+0.03)^35*0.03) -> 21.48722 | F13: =((1+0.035)^35-1)/((1+0.035)^35*0.035) -> 20.000661 | G13: =((1+0.04)^35-1)/((1+0.04)^35*0.04) -> 18.664613 | H13: =((1+0.045)^35-1)/((1+0.045)^35*0.045) -> 17.461012 | I13: =((1+0.05)^35-1)/((1+0.05)^35*0.05) -> 16.374194 | J13: =((1+0.06)^35-1)/((1+0.06)^35*0.06) -> 14.498246 | K13: =((1+0.07)^35-1)/((1+0.07)^35*0.07) -> 12.947672 | L13: =((1+0.08)^35-1)/((1+0.08)^35*0.08) -> 11.654568
B14: 40 | C14: =((1+0.02)^40-1)/((1+0.02)^40*0.02) -> 27.355479 | D14: =((1+0.025)^40-1)/((1+0.025)^40*0.025) -> 25.102775 | E14: =((1+0.03)^40-1)/((1+0.03)^40*0.03) -> 23.114772 | F14: =((1+0.035)^40-1)/((1+0.035)^40*0.035) -> 21.355072 | G14: =((1+0.04)^40-1)/((1+0.04)^40*0.04) -> 19.792774 | H14: =((1+0.045)^40-1)/((1+0.045)^40*0.045) -> 18.401584 | I14: =((1+0.05)^40-1)/((1+0.05)^40*0.05) -> 17.159086 | J14: =((1+0.06)^40-1)/((1+0.06)^40*0.06) -> 15.046297 | K14: =((1+0.07)^40-1)/((1+0.07)^40*0.07) -> 13.331709 | L14: =((1+0.08)^40-1)/((1+0.08)^40*0.08) -> 11.924613
B15: 45 | C15: =((1+0.02)^45-1)/((1+0.02)^45*0.02) -> 29.49016 | D15: =((1+0.025)^45-1)/((1+0.025)^45*0.025) -> 26.833024 | E15: =((1+0.03)^45-1)/((1+0.03)^45*0.03) -> 24.518713 | F15: =((1+0.035)^45-1)/((1+0.035)^45*0.035) -> 22.49545 | G15: =((1+0.04)^45-1)/((1+0.04)^45*0.04) -> 20.72004 | H15: =((1+0.045)^45-1)/((1+0.045)^45*0.045) -> 19.156347 | I15: =((1+0.05)^45-1)/((1+0.05)^45*0.05) -> 17.77407 | J15: =((1+0.06)^45-1)/((1+0.06)^45*0.06) -> 15.455832 | K15: =((1+0.07)^45-1)/((1+0.07)^45*0.07) -> 13.605522 | L15: =((1+0.08)^45-1)/((1+0.08)^45*0.08) -> 12.108402
B16: 50 | C16: =((1+0.02)^50-1)/((1+0.02)^50*0.02) -> 31.423606 | D16: =((1+0.025)^50-1)/((1+0.025)^50*0.025) -> 28.362312 | E16: =((1+0.03)^50-1)/((1+0.03)^50*0.03) -> 25.729764 | F16: =((1+0.035)^50-1)/((1+0.035)^50*0.035) -> 23.455618 | G16: =((1+0.04)^50-1)/((1+0.04)^50*0.04) -> 21.482185 | H16: =((1+0.045)^50-1)/((1+0.045)^50*0.045) -> 19.762008 | I16: =((1+0.05)^50-1)/((1+0.05)^50*0.05) -> 18.255925 | J16: =((1+0.06)^50-1)/((1+0.06)^50*0.06) -> 15.761861 | K16: =((1+0.07)^50-1)/((1+0.07)^50*0.07) -> 13.800746 | L16: =((1+0.08)^50-1)/((1+0.08)^50*0.08) -> 12.233485
B17: 55 | C17: =((1+0.02)^55-1)/((1+0.02)^55*0.02) -> 33.174788 | D17: =((1+0.025)^55-1)/((1+0.025)^55*0.025) -> 29.713979 | E17: =((1+0.03)^55-1)/((1+0.03)^55*0.03) -> 26.774428 | F17: =((1+0.035)^55-1)/((1+0.035)^55*0.035) -> 24.264053 | G17: =((1+0.04)^55-1)/((1+0.04)^55*0.04) -> 22.108612 | H17: =((1+0.045)^55-1)/((1+0.045)^55*0.045) -> 20.248021 | I17: =((1+0.05)^55-1)/((1+0.05)^55*0.05) -> 18.633472 | J17: =((1+0.06)^55-1)/((1+0.06)^55*0.06) -> 15.990543 | K17: =((1+0.07)^55-1)/((1+0.07)^55*0.07) -> 13.939939 | L17: =((1+0.08)^55-1)/((1+0.08)^55*0.08) -> 12.318614
B18: 60 | C18: =((1+0.02)^60-1)/((1+0.02)^60*0.02) -> 34.760887 | D18: =((1+0.025)^60-1)/((1+0.025)^60*0.025) -> 30.908656 | E18: =((1+0.03)^60-1)/((1+0.03)^60*0.03) -> 27.675564 | F18: =((1+0.035)^60-1)/((1+0.035)^60*0.035) -> 24.944734 | G18: =((1+0.04)^60-1)/((1+0.04)^60*0.04) -> 22.62349 | H18: =((1+0.045)^60-1)/((1+0.045)^60*0.045) -> 20.638022 | I18: =((1+0.05)^60-1)/((1+0.05)^60*0.05) -> 18.92929 | J18: =((1+0.06)^60-1)/((1+0.06)^60*0.06) -> 16.161428 | K18: =((1+0.07)^60-1)/((1+0.07)^60*0.07) -> 14.039181 | L18: =((1+0.08)^60-1)/((1+0.08)^60*0.08) -> 12.376552
B19: 65 | C19: =((1+0.02)^65-1)/((1+0.02)^65*0.02) -> 36.197466 | D19: =((1+0.025)^65-1)/((1+0.025)^65*0.025) -> 31.964577 | E19: =((1+0.03)^65-1)/((1+0.03)^65*0.03) -> 28.452892 | F19: =((1+0.035)^65-1)/((1+0.035)^65*0.035) -> 25.517849 | G19: =((1+0.04)^65-1)/((1+0.04)^65*0.04) -> 23.046682 | H19: =((1+0.045)^65-1)/((1+0.045)^65*0.045) -> 20.950979 | I19: =((1+0.05)^65-1)/((1+0.05)^65*0.05) -> 19.16107 | J19: =((1+0.06)^65-1)/((1+0.06)^65*0.06) -> 16.289123 | K19: =((1+0.07)^65-1)/((1+0.07)^65*0.07) -> 14.10994 | L19: =((1+0.08)^65-1)/((1+0.08)^65*0.08) -> 12.415983
B20: 70 | C20: =((1+0.02)^70-1)/((1+0.02)^70*0.02) -> 37.498619 | D20: =((1+0.025)^70-1)/((1+0.025)^70*0.025) -> 32.897857 | E20: =((1+0.03)^70-1)/((1+0.03)^70*0.03) -> 29.123421 | F20: =((1+0.035)^70-1)/((1+0.035)^70*0.035) -> 26.000397 | G20: =((1+0.04)^70-1)/((1+0.04)^70*0.04) -> 23.394515 | H20: =((1+0.045)^70-1)/((1+0.045)^70*0.045) -> 21.202112 | I20: =((1+0.05)^70-1)/((1+0.05)^70*0.05) -> 19.342677 | J20: =((1+0.06)^70-1)/((1+0.06)^70*0.06) -> 16.384544 | K20: =((1+0.07)^70-1)/((1+0.07)^70*0.07) -> 14.160389 | L20: =((1+0.08)^70-1)/((1+0.08)^70*0.08) -> 12.44282
B21: 75 | C21: =((1+0.02)^75-1)/((1+0.02)^75*0.02) -> 38.677114 | D21: =((1+0.025)^75-1)/((1+0.025)^75*0.025) -> 33.72274 | E21: =((1+0.03)^75-1)/((1+0.03)^75*0.03) -> 29.701826 | F21: =((1+0.035)^75-1)/((1+0.035)^75*0.035) -> 26.406689 | G21: =((1+0.04)^75-1)/((1+0.04)^75*0.04) -> 23.680408 | H21: =((1+0.045)^75-1)/((1+0.045)^75*0.045) -> 21.403634 | I21: =((1+0.05)^75-1)/((1+0.05)^75*0.05) -> 19.48497 | J21: =((1+0.06)^75-1)/((1+0.06)^75*0.06) -> 16.455848 | K21: =((1+0.07)^75-1)/((1+0.07)^75*0.07) -> 14.196359 | L21: =((1+0.08)^75-1)/((1+0.08)^75*0.08) -> 12.461084
B22: 80 | C22: =((1+0.02)^80-1)/((1+0.02)^80*0.02) -> 39.744514 | D22: =((1+0.025)^80-1)/((1+0.025)^80*0.025) -> 34.451817 | E22: =((1+0.03)^80-1)/((1+0.03)^80*0.03) -> 30.200763 | F22: =((1+0.035)^80-1)/((1+0.035)^80*0.035) -> 26.748776 | G22: =((1+0.04)^80-1)/((1+0.04)^80*0.04) -> 23.915392 | H22: =((1+0.045)^80-1)/((1+0.045)^80*0.045) -> 21.565345 | I22: =((1+0.05)^80-1)/((1+0.05)^80*0.05) -> 19.59646 | J22: =((1+0.06)^80-1)/((1+0.06)^80*0.06) -> 16.509131 | K22: =((1+0.07)^80-1)/((1+0.07)^80*0.07) -> 14.222005 | L22: =((1+0.08)^80-1)/((1+0.08)^80*0.08) -> 12.473514
B24: ABZINSUNGSFAKTOR q⁻ⁿ = 1 / (1+p)ⁿ · Spalten = Zinssatz p
B25: n \ p | C25: 0.02 | D25: 0.025 | E25: 0.03 | F25: 0.035 | G25: 0.04 | H25: 0.045 | I25: 0.05 | J25: 0.06 | K25: 0.07 | L25: 0.08
B26: 5 | C26: =1/(1+0.02)^5 -> 0.90573081 | D26: =1/(1+0.025)^5 -> 0.88385429 | E26: =1/(1+0.03)^5 -> 0.86260878 | F26: =1/(1+0.035)^5 -> 0.84197317 | G26: =1/(1+0.04)^5 -> 0.82192711 | H26: =1/(1+0.045)^5 -> 0.80245105 | I26: =1/(1+0.05)^5 -> 0.78352617 | J26: =1/(1+0.06)^5 -> 0.74725817 | K26: =1/(1+0.07)^5 -> 0.71298618 | L26: =1/(1+0.08)^5 -> 0.6805832
B27: 10 | C27: =1/(1+0.02)^10 -> 0.8203483 | D27: =1/(1+0.025)^10 -> 0.7811984 | E27: =1/(1+0.03)^10 -> 0.74409391 | F27: =1/(1+0.035)^10 -> 0.70891881 | G27: =1/(1+0.04)^10 -> 0.67556417 | H27: =1/(1+0.045)^10 -> 0.64392768 | I27: =1/(1+0.05)^10 -> 0.61391325 | J27: =1/(1+0.06)^10 -> 0.55839478 | K27: =1/(1+0.07)^10 -> 0.50834929 | L27: =1/(1+0.08)^10 -> 0.46319349
B28: 15 | C28: =1/(1+0.02)^15 -> 0.74301473 | D28: =1/(1+0.025)^15 -> 0.69046556 | E28: =1/(1+0.03)^15 -> 0.64186195 | F28: =1/(1+0.035)^15 -> 0.59689062 | G28: =1/(1+0.04)^15 -> 0.5552645 | H28: =1/(1+0.045)^15 -> 0.51672044 | I28: =1/(1+0.05)^15 -> 0.4810171 | J28: =1/(1+0.06)^15 -> 0.41726506 | K28: =1/(1+0.07)^15 -> 0.36244602 | L28: =1/(1+0.08)^15 -> 0.3152417
B29: 20 | C29: =1/(1+0.02)^20 -> 0.67297133 | D29: =1/(1+0.025)^20 -> 0.61027094 | E29: =1/(1+0.03)^20 -> 0.55367575 | F29: =1/(1+0.035)^20 -> 0.50256588 | G29: =1/(1+0.04)^20 -> 0.45638695 | H29: =1/(1+0.045)^20 -> 0.41464286 | I29: =1/(1+0.05)^20 -> 0.37688948 | J29: =1/(1+0.06)^20 -> 0.31180473 | K29: =1/(1+0.07)^20 -> 0.258419 | L29: =1/(1+0.08)^20 -> 0.21454821
B30: 25 | C30: =1/(1+0.02)^25 -> 0.60953087 | D30: =1/(1+0.025)^25 -> 0.53939059 | E30: =1/(1+0.03)^25 -> 0.47760557 | F30: =1/(1+0.035)^25 -> 0.42314699 | G30: =1/(1+0.04)^25 -> 0.3751168 | H30: =1/(1+0.045)^25 -> 0.3327306 | I30: =1/(1+0.05)^25 -> 0.29530277 | J30: =1/(1+0.06)^25 -> 0.23299863 | K30: =1/(1+0.07)^25 -> 0.18424918 | L30: =1/(1+0.08)^25 -> 0.1460179
B31: 30 | C31: =1/(1+0.02)^30 -> 0.55207089 | D31: =1/(1+0.025)^30 -> 0.47674269 | E31: =1/(1+0.03)^30 -> 0.41198676 | F31: =1/(1+0.035)^30 -> 0.35627841 | G31: =1/(1+0.04)^30 -> 0.30831867 | H31: =1/(1+0.045)^30 -> 0.26700002 | I31: =1/(1+0.05)^30 -> 0.23137745 | J31: =1/(1+0.06)^30 -> 0.17411013 | K31: =1/(1+0.07)^30 -> 0.13136712 | L31: =1/(1+0.08)^30 -> 0.099377333
B32: 35 | C32: =1/(1+0.02)^35 -> 0.50002761 | D32: =1/(1+0.025)^35 -> 0.42137107 | E32: =1/(1+0.03)^35 -> 0.3553834 | F32: =1/(1+0.035)^35 -> 0.29997686 | G32: =1/(1+0.04)^35 -> 0.25341547 | H32: =1/(1+0.045)^35 -> 0.21425444 | I32: =1/(1+0.05)^35 -> 0.18129029 | J32: =1/(1+0.06)^35 -> 0.13010522 | K32: =1/(1+0.07)^35 -> 0.093662939 | L32: =1/(1+0.08)^35 -> 0.067634543
B33: 40 | C33: =1/(1+0.02)^40 -> 0.45289042 | D33: =1/(1+0.025)^40 -> 0.37243062 | E33: =1/(1+0.03)^40 -> 0.30655684 | F33: =1/(1+0.035)^40 -> 0.25257247 | G33: =1/(1+0.04)^40 -> 0.20828904 | H33: =1/(1+0.045)^40 -> 0.1719287 | I33: =1/(1+0.05)^40 -> 0.14204568 | J33: =1/(1+0.06)^40 -> 0.097222188 | K33: =1/(1+0.07)^40 -> 0.066780381 | L33: =1/(1+0.08)^40 -> 0.046030933
B34: 45 | C34: =1/(1+0.02)^45 -> 0.4101968 | D34: =1/(1+0.025)^45 -> 0.3291744 | E34: =1/(1+0.03)^45 -> 0.26443862 | F34: =1/(1+0.035)^45 -> 0.21265924 | G34: =1/(1+0.04)^45 -> 0.17119841 | H34: =1/(1+0.045)^45 -> 0.13796437 | I34: =1/(1+0.05)^45 -> 0.11129651 | J34: =1/(1+0.06)^45 -> 0.072650074 | K34: =1/(1+0.07)^45 -> 0.047613489 | L34: =1/(1+0.08)^45 -> 0.03132788
B35: 50 | C35: =1/(1+0.02)^50 -> 0.37152788 | D35: =1/(1+0.025)^50 -> 0.29094221 | E35: =1/(1+0.03)^50 -> 0.22810708 | F35: =1/(1+0.035)^50 -> 0.17905337 | G35: =1/(1+0.04)^50 -> 0.14071262 | H35: =1/(1+0.045)^50 -> 0.11070965 | I35: =1/(1+0.05)^50 -> 0.087203727 | J35: =1/(1+0.06)^50 -> 0.054288362 | K35: =1/(1+0.07)^50 -> 0.033947759 | L35: =1/(1+0.08)^50 -> 0.021321229
B36: 55 | C36: =1/(1+0.02)^55 -> 0.33650425 | D36: =1/(1+0.025)^55 -> 0.25715052 | E36: =1/(1+0.03)^55 -> 0.19676717 | F36: =1/(1+0.035)^55 -> 0.15075814 | G36: =1/(1+0.04)^55 -> 0.11565551 | H36: =1/(1+0.045)^55 -> 0.088839074 | I36: =1/(1+0.05)^55 -> 0.068326402 | J36: =1/(1+0.06)^55 -> 0.040567422 | K36: =1/(1+0.07)^55 -> 0.024204283 | L36: =1/(1+0.08)^55 -> 0.01451087
B37: 60 | C37: =1/(1+0.02)^60 -> 0.30478227 | D37: =1/(1+0.025)^60 -> 0.22728359 | E37: =1/(1+0.03)^60 -> 0.16973309 | F37: =1/(1+0.035)^60 -> 0.12693431 | G37: =1/(1+0.04)^60 -> 0.095060401 | H37: =1/(1+0.045)^60 -> 0.071289008 | I37: =1/(1+0.05)^60 -> 0.053535524 | J37: =1/(1+0.06)^60 -> 0.030314338 | K37: =1/(1+0.07)^60 -> 0.017257319 | L37: =1/(1+0.08)^60 -> 0.0098758542
B38: 65 | C38: =1/(1+0.02)^65 -> 0.27605069 | D38: =1/(1+0.025)^65 -> 0.20088557 | E38: =1/(1+0.03)^65 -> 0.14641325 | F38: =1/(1+0.035)^65 -> 0.10687528 | G38: =1/(1+0.04)^65 -> 0.07813272 | H38: =1/(1+0.045)^65 -> 0.057205939 | I38: =1/(1+0.05)^65 -> 0.041946484 | J38: =1/(1+0.06)^65 -> 0.022652637 | K38: =1/(1+0.07)^65 -> 0.01230423 | L38: =1/(1+0.08)^65 -> 0.0067213404
B39: 70 | C39: =1/(1+0.02)^70 -> 0.25002761 | D39: =1/(1+0.025)^70 -> 0.17755358 | E39: =1/(1+0.03)^70 -> 0.12629736 | F39: =1/(1+0.035)^70 -> 0.089986118 | G39: =1/(1+0.04)^70 -> 0.064219401 | H39: =1/(1+0.045)^70 -> 0.045904966 | I39: =1/(1+0.05)^70 -> 0.032866168 | J39: =1/(1+0.06)^70 -> 0.016927368 | K39: =1/(1+0.07)^70 -> 0.0087727461 | L39: =1/(1+0.08)^70 -> 0.0045744314
B40: 75 | C40: =1/(1+0.02)^75 -> 0.22645771 | D40: =1/(1+0.025)^75 -> 0.15693149 | E40: =1/(1+0.03)^75 -> 0.10894521 | F40: =1/(1+0.035)^75 -> 0.075765896 | G40: =1/(1+0.04)^75 -> 0.052783666 | H40: =1/(1+0.045)^75 -> 0.036836488 | I40: =1/(1+0.05)^75 -> 0.025751502 | J40: =1/(1+0.06)^75 -> 0.012649114 | K40: =1/(1+0.07)^75 -> 0.0062548468 | L40: =1/(1+0.08)^75 -> 0.0031132811
B41: 80 | C41: =1/(1+0.02)^80 -> 0.20510973 | D41: =1/(1+0.025)^80 -> 0.13870457 | E41: =1/(1+0.03)^80 -> 0.093977097 | F41: =1/(1+0.035)^80 -> 0.063792852 | G41: =1/(1+0.04)^80 -> 0.043384326 | H41: =1/(1+0.045)^80 -> 0.029559478 | I41: =1/(1+0.05)^80 -> 0.020176976 | J41: =1/(1+0.06)^80 -> 0.0094521538 | K41: =1/(1+0.07)^80 -> 0.0044596193 | L41: =1/(1+0.08)^80 -> 0.0021188468
B43: Nachschüssige Rente. Zwischenwerte ggf. linear interpolieren. Werte entsprechen den amtlichen Vervielfältigertabellen (Anlage zur ImmoWertV / WertR).
